LICENSE.txt
MANIFEST.in
NOTICE.txt
README.md
setup.cfg
setup.py
amazon_kclpy/__init__.py
amazon_kclpy/dispatch.py
amazon_kclpy/kcl.py
amazon_kclpy/messages.py
amazon_kclpy/jars/__init__.py
amazon_kclpy/v2/__init__.py
amazon_kclpy/v2/processor.py
amazon_kclpy_ext.egg-info/PKG-INFO
amazon_kclpy_ext.egg-info/SOURCES.txt
amazon_kclpy_ext.egg-info/dependency_links.txt
amazon_kclpy_ext.egg-info/not-zip-safe
amazon_kclpy_ext.egg-info/requires.txt
amazon_kclpy_ext.egg-info/top_level.txt
samples/__init__.py
samples/amazon_kclpy_helper.py
samples/sample.properties
samples/sample_kclpy_app.py
samples/sample_kinesis_wordputter.py
test/test_amazon_kclpy.py
test/test_amazon_kclpy_input_output_integration.py