Metadata-Version: 1.0
Name: amazon_kclpy-ext
Version: 1.5.1
Summary: A python interface for the Amazon Kinesis Client Library MultiLangDaemon
Home-page: https://github.com/awslabs/amazon-kinesis-client-python
Author: UNKNOWN
Author-email: UNKNOWN
License: Amazon Software License
Keywords: amazon kinesis client library python
Platform: UNKNOWN
